zerodhawrapper/__init__.py
zerodhawrapper/zd.py
zerodhawrapper-1.3.dist-info/METADATA
zerodhawrapper-1.3.dist-info/WHEEL
zerodhawrapper-1.3.dist-info/top_level.txt
zerodhawrapper-1.3.dist-info/RECORD
