Metadata-Version: 2.4
Name: zerodhawrapper
Version: 1.3
Summary: A Python wrapper for the Zerodha API that simplifies interaction with Zerodha's trading platform
Home-page: https://github.com/kunalAgarwal35/zerodha_wrapper
Author: Kunal Agarwal
Author-email: kunal.95a@gmail.com
Classifier: Programming Language :: Python :: 3
Classifier: License :: OSI Approved :: MIT License
Classifier: Operating System :: OS Independent
Requires-Python: >=3.6
Requires-Dist: kiteconnect
Requires-Dist: pandas
Requires-Dist: furl
Requires-Dist: nsetools
Requires-Dist: prettytable
Requires-Dist: pyotp
Requires-Dist: webdriver-manager
Requires-Dist: selenium
Dynamic: author
Dynamic: author-email
Dynamic: classifier
Dynamic: description
Dynamic: description-content-type
Dynamic: home-page
Dynamic: requires-dist
Dynamic: requires-python
Dynamic: summary
